spentcommnew/__init__.py
spentcommnew/embedding.py
spentcommnew/llm_clients.py
spentcommnew/prompts.py
spentcommnew/sample_queries.py
spentcommnew/taxonomy.py
spentcommnew/test_file.py
spentcommnew-1.0.0.dist-info/LICENSE
spentcommnew-1.0.0.dist-info/WHEEL
spentcommnew-1.0.0.dist-info/METADATA
spentcommnew-1.0.0.dist-info/RECORD
