Metadata-Version: 2.1
Name: spentcommnew
Version: 1.0.0
Summary: __version__ = "x.y.z"
Author-email: me <shemagen1@publicisgroupe.net>
Classifier: License :: OSI Approved :: MIT License
Project-URL: Home, https://upload.pypi.org/legacy/
